time_dict/__init__.py
time_dict/time_dict.py
time_dict/updater.py
time_dictionary/__init__.py
time_dictionary/time_dict.py
time_dictionary/updater.py
timedict-0.0.3.dist-info/LICENSE
timedict-0.0.3.dist-info/METADATA
timedict-0.0.3.dist-info/WHEEL
timedict-0.0.3.dist-info/top_level.txt
timedict-0.0.3.dist-info/RECORD
