Metadata-Version: 2.1
Name: timedict
Version: 0.0.3
Summary: A self updating dictionary like structure
Home-page: https://github.com/Matshec/time_dict
Author: Matshec
Author-email: mmasakra@gmail.com
License: UNKNOWN
Platform: UNKNOWN
Classifier: Programming Language :: Python :: 3
Classifier: License :: OSI Approved :: MIT License
Classifier: Operating System :: OS Independent
Requires-Python: >=3.5
